[
    {
        "title": "Conference",
        "start": "2022-07-26",
        "end": "2022-07-28"
    },
    {
        "title": "Meeting",
        "start": "2022-07-27T10:30:00+00:00",
        "end": "2022-07-27T12:30:00+00:00"
    },
    {
        "title": "Lunch",
        "start": "2022-07-27T12:00:00+00:00"
    },
    {
        "title": "Birthday Party",
        "start": "2022-07-28T07:00:00+00:00"
    },
    {
        "url": "http:\/\/google.com\/",
        "title": "Click for Google",
        "start": "2022-07-28"
    },
    {
        "title": "Test",
        "start": "2022-09-28"
    }
]